wicked_historian/__init__.py
wicked_historian/apps.py
wicked_historian/checks.py
wicked_historian/deletion.py
wicked_historian/encoder.py
wicked_historian/handlers.py
wicked_historian/models.py
wicked_historian/signals_exclusion.py
wicked_historian/usersmuggler.py
wicked_historian/utils.py
wicked_historian/compat/__init__.py
wicked_historian/compat/mariadb.py
wicked_historian/compat/mysql.py
wicked_historian/compat/postgres.py
wicked_historian/tests/__init__.py
wicked_historian/tests/test_usersmuggler.py
django_wicked_historian-1.0.0.dist-info/LICENSE
django_wicked_historian-1.0.0.dist-info/METADATA
django_wicked_historian-1.0.0.dist-info/WHEEL
django_wicked_historian-1.0.0.dist-info/top_level.txt
django_wicked_historian-1.0.0.dist-info/RECORD
