Metadata-Version: 2.1
Name: django-wicked-historian
Version: 1.0.0
Summary: A complete solution for creating automatic history of Django models.
Author: IIIT
Author-email: github@iiit.pl
License: UNKNOWN
Platform: UNKNOWN
Classifier: Environment :: Web Environment
Classifier: Framework :: Django
Classifier: Intended Audience :: Developers
Classifier: Operating System :: OS Independent
Classifier: Programming Language :: Python :: 3.6
Classifier: Programming Language :: Python :: 3.8
Classifier: Programming Language :: Python :: 3.10
License-File: LICENSE
Requires-Dist: Django (<3.0,>=2.1)
Requires-Dist: django-diffable (>=1.0.0)
Provides-Extra: django-jsonfield
Requires-Dist: django-jsonfield (>=1.0.1) ; extra == 'django-jsonfield'
Provides-Extra: mysql
Requires-Dist: django-mysql (>=2.2.0) ; extra == 'mysql'
Provides-Extra: postgres
Requires-Dist: psycopg2 (>=2.6.2) ; extra == 'postgres'
